[{"mSpeed":0,"mCalorie":0,"mDistance":0,"mWalkStepCount":0,"mNowHealthyStep":0,"mTotalActiveTime":0,"mTimeUnit":600000,"mStepCount":0,"mRunStepCount":0,"mStartTime":0},{"mSpeed":0,"mCalorie":0,"mDistance":0,"mWalkStepCount":0,"mNowHealthyStep":0,"mTotalActiveTime":0,"mTimeUnit":600000,"mStepCount":0,"mRunStepCount":0,"mStartTime":0},{"mSpeed":0,"mCalorie":0,"mDistance":0,"mWalkStepCount":0,"mNowHealthyStep":0,"mTotalActiveTime":0,"mTimeUnit":600000,"mStepCount":0,"mRunStepCount":0,"mStartTime":0},{"mSpeed":0,"mCalorie":0,"mDistance":0,"mWalkStepCount":0,"mNowHealthyStep":0,"mTotalActiveTime":0,"mTimeUnit":600000,"mStepCount":0,"mRunStepCount":0,"mStartTime":0},{"mSpeed":0,"mCalorie":0,"mDistance":0,"mWalkStepCount":0,"mNowHealthyStep":0,"mTotalActiveTime":0,"mTimeUnit":600000,"mStepCount":0,"mRunStepCount":0,"mStartTime":0},{"mSpeed":0,"mCalorie":0,"mDistance":0,"mWalkStepCount":0,"mNowHealthyStep":0,"mTotalActiveTime":0,"mTimeUnit":600000,"mStepCount":0,"mRunStepCount":0,"mStartTime":0},{"mSpeed":0,"mCalorie":0,"mDistance":0,"mWalkStepCount":0,"mNowHealthyStep":0,"mTotalActiveTime":0,"mTimeUnit":600000,"mStepCount":0,"mRunStepCount":0,"mStartTime":0},{"mSpeed":0,"mCalorie":0,"mDistance":0,"mWalkStepCount":0,"mNowHealthyStep":0,"mTotalActiveTime":0,"mTimeUnit":600000,"mStepCount":0,"mRunStepCount":0,"mStartTime":0},{"mSpeed":0,"mCalorie":0,"mDistance":0,"mWalkStepCount":0,"mNowHealthyStep":0,"mTotalActiveTime":0,"mTimeUnit":600000,"mStepCount":0,"mRunStepCount":0,"mStartTime":0},{"mSpeed":0,"mCalorie":0,"mDistance":0,"mWalkStepCount":0,"mNowHealthyStep":0,"mTotalActiveTime":0,"mTimeUnit":600000,"mStepCount":0,"mRunStepCount":0,"mStartTime":0},{"mSpeed":0,"mCalorie":0,"mDistance":0,"mWalkStepCount":0,"mNowHealthyStep":0,"mTotalActiveTime":0,"mTimeUnit":600000,"mStepCount":0,"mRunStepCount":0,"mStartTime":0},{"mSpeed":0,"mCalorie":0,"mDistance":0,"mWalkStepCount":0,"mNowHealthyStep":0,"mTotalActiveTime":0,"mTimeUnit":600000,"mStepCount":0,"mRunStepCount":0,"mStartTime":0},{"mSpeed":0,"mCalorie":0,"mDistance":0,"mWalkStepCount":0,"mNowHealthyStep":0,"mTotalActiveTime":0,"mTimeUnit":600000,"mStepCount":0,"mRunStepCount":0,"mStartTime":0},{"mSpeed":0,"mCalorie":0,"mDistance":0,"mWalkStepCount":0,"mNowHealthyStep":0,"mTotalActiveTime":0,"mTimeUnit":600000,"mStepCount":0,"mRunStepCount":0,"mStartTime":0},{"mSpeed":0,"mCalorie":0,"mDistance":0,"mWalkStepCount":0,"mNowHealthyStep":0,"mTotalActiveTime":0,"mTimeUnit":600000,"mStepCount":0,"mRunStepCount":0,"mStartTime":0},{"mSpeed":0,"mCalorie":0,"mDistance":0,"mWalkStepCount":0,"mNowHealthyStep":0,"mTotalActiveTime":0,"mTimeUnit":600000,"mStepCount":0,"mRunStepCount":0,"mStartTime":0},{"mSpeed":0,"mCalorie":0,"mDistance":0,"mWalkStepCount":0,"mNowHealthyStep":0,"mTotalActiveTime":0,"mTimeUnit":600000,"mStepCount":0,"mRunStepCount":0,"mStartTime":0},{"mSpeed":0,"mCalorie":0,"mDistance":0,"mWalkStepCount":0,"mNowHealthyStep":0,"mTotalActiveTime":0,"mTimeUnit":600000,"mStepCount":0,"mRunStepCount":0,"mStartTime":0},{"mSpeed":0,"mCalorie":0,"mDistance":0,"mWalkStepCount":0,"mNowHealthyStep":0,"mTotalActiveTime":0,"mTimeUnit":600000,"mStepCount":0,"mRunStepCount":0,"mStartTime":0},{"mSpeed":0,"mCalorie":0,"mDistance":0,"mWalkStepCount":0,"mNowHealthyStep":0,"mTotalActiveTime":0,"mTimeUnit":600000,"mStepCount":0,"mRunStepCount":0,"mStartTime":0},{"mSpeed":0,"mCalorie":0,"mDistance":0,"mWalkStepCount":0,"mNowHealthyStep":0,"mTotalActiveTime":0,"mTimeUnit":600000,"mStepCount":0,"mRunStepCount":0,"mStartTime":0},{"mSpeed":0,"mCalorie":0,"mDistance":0,"mWalkStepCount":0,"mNowHealthyStep":0,"mTotalActiveTime":0,"mTimeUnit":600000,"mStepCount":0,"mRunStepCount":0,"mStartTime":0},{"mSpeed":0,"mCalorie":0,"mDistance":0,"mWalkStepCount":0,"mNowHealthyStep":0,"mTotalActiveTime":0,"mTimeUnit":600000,"mStepCount":0,"mRunStepCount":0,"mStartTime":0},{"mSpeed":0,"mCalorie":0,"mDistance":0,"mWalkStepCount":0,"mNowHealthyStep":0,"mTotalActiveTime":0,"mTimeUnit":600000,"mStepCount":0,"mRunStepCount":0,"mStartTime":0},{"mSpeed":0,"mCalorie":0,"mDistance":0,"mWalkStepCount":0,"mNowHealthyStep":0,"mTotalActiveTime":0,"mTimeUnit":600000,"mStepCount":0,"mRunStepCount":0,"mStartTime":0},{"mSpeed":0,"mCalorie":0,"mDistance":0,"mWalkStepCount":0,"mNowHealthyStep":0,"mTotalActiveTime":0,"mTimeUnit":600000,"mStepCount":0,"mRunStepCount":0,"mStartTime":0},{"mSpeed":0,"mCalorie":0,"mDistance":0,"mWalkStepCount":0,"mNowHealthyStep":0,"mTotalActiveTime":0,"mTimeUnit":600000,"mStepCount":0,"mRunStepCount":0,"mStartTime":0},{"mSpeed":0,"mCalorie":0,"mDistance":0,"mWalkStepCount":0,"mNowHealthyStep":0,"mTotalActiveTime":0,"mTimeUnit":600000,"mStepCount":0,"mRunStepCount":0,"mStartTime":0},{"mSpeed":0,"mCalorie":0,"mDistance":0,"mWalkStepCount":0,"mNowHealthyStep":0,"mTotalActiveTime":0,"mTimeUnit":600000,"mStepCount":0,"mRunStepCount":0,"mStartTime":0},{"mSpeed":0,"mCalorie":0,"mDistance":0,"mWalkStepCount":0,"mNowHealthyStep":0,"mTotalActiveTime":0,"mTimeUnit":600000,"mStepCount":0,"mRunStepCount":0,"mStartTime":0},{"mSpeed":0,"mCalorie":0,"mDistance":0,"mWalkStepCount":0,"mNowHealthyStep":0,"mTotalActiveTime":0,"mTimeUnit":600000,"mStepCount":0,"mRunStepCount":0,"mStartTime":0},{"mSpeed":0,"mCalorie":0,"mDistance":0,"mWalkStepCount":0,"mNowHealthyStep":0,"mTotalActiveTime":0,"mTimeUnit":600000,"mStepCount":0,"mRunStepCount":0,"mStartTime":0},{"mSpeed":0,"mCalorie":0,"mDistance":0,"mWalkStepCount":0,"mNowHealthyStep":0,"mTotalActiveTime":0,"mTimeUnit":600000,"mStepCount":0,"mRunStepCount":0,"mStartTime":0},{"mSpeed":0,"mCalorie":0,"mDistance":0,"mWalkStepCount":0,"mNowHealthyStep":0,"mTotalActiveTime":0,"mTimeUnit":600000,"mStepCount":0,"mRunStepCount":0,"mStartTime":0},{"mSpeed":0,"mCalorie":0,"mDistance":0,"mWalkStepCount":0,"mNowHealthyStep":0,"mTotalActiveTime":0,"mTimeUnit":600000,"mStepCount":0,"mRunStepCount":0,"mStartTime":0},{"mSpeed":0,"mCalorie":0,"mDistance":0,"mWalkStepCount":0,"mNowHealthyStep":0,"mTotalActiveTime":0,"mTimeUnit":600000,"mStepCount":0,"mRunStepCount":0,"mStartTime":0},{"mSpeed":0,"mCalorie":0,"mDistance":0,"mWalkStepCount":0,"mNowHealthyStep":0,"mTotalActiveTime":0,"mTimeUnit":600000,"mStepCount":0,"mRunStepCount":0,"mStartTime":0},{"mSpeed":0,"mCalorie":0,"mDistance":0,"mWalkStepCount":0,"mNowHealthyStep":0,"mTotalActiveTime":0,"mTimeUnit":600000,"mStepCount":0,"mRunStepCount":0,"mStartTime":0},{"mSpeed":0,"mCalorie":0,"mDistance":0,"mWalkStepCount":0,"mNowHealthyStep":0,"mTotalActiveTime":0,"mTimeUnit":600000,"mStepCount":0,"mRunStepCount":0,"mStartTime":0},{"mSpeed":0,"mCalorie":0,"mDistance":0,"mWalkStepCount":0,"mNowHealthyStep":0,"mTotalActiveTime":0,"mTimeUnit":600000,"mStepCount":0,"mRunStepCount":0,"mStartTime":0},{"mSpeed":0,"mCalorie":0,"mDistance":0,"mWalkStepCount":0,"mNowHealthyStep":0,"mTotalActiveTime":0,"mTimeUnit":600000,"mStepCount":0,"mRunStepCount":0,"mStartTime":0},{"mSpeed":0,"mCalorie":0,"mDistance":0,"mWalkStepCount":0,"mNowHealthyStep":0,"mTotalActiveTime":0,"mTimeUnit":600000,"mStepCount":0,"mRunStepCount":0,"mStartTime":0},{"mSpeed":4.8279614448547363,"mCalorie":20.160000000000199,"mDistance":432.3419999999993,"mWalkStepCount":576,"mNowHealthyStep":0,"mTotalActiveTime":322378.56092164782,"mTimeUnit":600000,"mStepCount":576,"mRunStepCount":0,"mStartTime":0},{"mSpeed":4.8753328323364258,"mCalorie":16.689999999999472,"mDistance":359.61199999999428,"mWalkStepCount":475,"mNowHealthyStep":0,"mTotalActiveTime":265541.50989079726,"mTimeUnit":600000,"mStepCount":475,"mRunStepCount":0,"mStartTime":0},{"mSpeed":5.128507137298584,"mCalorie":5.8899999999999642,"mDistance":128.81799999999845,"mWalkStepCount":168,"mNowHealthyStep":0,"mTotalActiveTime":90424.908246294319,"mTimeUnit":600000,"mStepCount":168,"mRunStepCount":0,"mStartTime":0},{"mSpeed":7.6999998092651367,"mCalorie":0.28999999999999998,"mDistance":9.0700000000000003,"mWalkStepCount":11,"mNowHealthyStep":0,"mTotalActiveTime":4240.5195855603797,"mTimeUnit":600000,"mStepCount":11,"mRunStepCount":0,"mStartTime":0},{"mSpeed":4.73046875,"mCalorie":8.7300000000000004,"mDistance":183.90000000000001,"mWalkStepCount":245,"mNowHealthyStep":0,"mTotalActiveTime":139952.30365021637,"mTimeUnit":600000,"mStepCount":245,"mRunStepCount":0,"mStartTime":0},{"mSpeed":4.8744044303894043,"mCalorie":10.879000000000321,"mDistance":237.14699999999459,"mWalkStepCount":316,"mNowHealthyStep":0,"mTotalActiveTime":175145.34115459665,"mTimeUnit":600000,"mStepCount":316,"mRunStepCount":0,"mStartTime":0},{"mSpeed":4.6158461570739746,"mCalorie":6.0000000000003091,"mDistance":132.71999999999969,"mWalkStepCount":178,"mNowHealthyStep":0,"mTotalActiveTime":103511.25324887047,"mTimeUnit":600000,"mStepCount":178,"mRunStepCount":0,"mStartTime":0},{"mSpeed":4.396751880645752,"mCalorie":6.630000000000182,"mDistance":142.4590000000008,"mWalkStepCount":194,"mNowHealthyStep":0,"mTotalActiveTime":116643.46950614099,"mTimeUnit":600000,"mStepCount":194,"mRunStepCount":0,"mStartTime":0},{"mSpeed":4.805396556854248,"mCalorie":7.2610000000000765,"mDistance":157.70099999999977,"mWalkStepCount":211,"mNowHealthyStep":0,"mTotalActiveTime":118142.92074405398,"mTimeUnit":600000,"mStepCount":211,"mRunStepCount":0,"mStartTime":0},{"mSpeed":4.2634406089782715,"mCalorie":8.2200000000000184,"mDistance":171.38899999999705,"mWalkStepCount":236,"mNowHealthyStep":0,"mTotalActiveTime":144718.89942104116,"mTimeUnit":600000,"mStepCount":236,"mRunStepCount":0,"mStartTime":0},{"mSpeed":4.8023014068603516,"mCalorie":14.860000000000001,"mDistance":319.05599999999163,"mWalkStepCount":426,"mNowHealthyStep":0,"mTotalActiveTime":239177.32340260438,"mTimeUnit":600000,"mStepCount":426,"mRunStepCount":0,"mStartTime":0},{"mSpeed":0,"mCalorie":0,"mDistance":0,"mWalkStepCount":0,"mNowHealthyStep":0,"mTotalActiveTime":0,"mTimeUnit":600000,"mStepCount":0,"mRunStepCount":0,"mStartTime":0},{"mSpeed":5.1752738952636719,"mCalorie":1.8399999999997454,"mDistance":38.803999999993827,"mWalkStepCount":44,"mNowHealthyStep":0,"mTotalActiveTime":26992.658326320441,"mTimeUnit":600000,"mStepCount":50,"mRunStepCount":6,"mStartTime":0},{"mSpeed":4.8993172645568848,"mCalorie":13.620000000001475,"mDistance":282.26400000001479,"mWalkStepCount":376,"mNowHealthyStep":0,"mTotalActiveTime":207406.52496082726,"mTimeUnit":600000,"mStepCount":378,"mRunStepCount":2,"mStartTime":0},{"mSpeed":5.4734840393066406,"mCalorie":5.7000000000002,"mDistance":126.13899999999704,"mWalkStepCount":162,"mNowHealthyStep":0,"mTotalActiveTime":82963.6845508853,"mTimeUnit":600000,"mStepCount":163,"mRunStepCount":1,"mStartTime":0},{"mSpeed":4.6077790260314941,"mCalorie":7.1799999999998541,"mDistance":151.54299999999813,"mWalkStepCount":204,"mNowHealthyStep":0,"mTotalActiveTime":118398.64452645478,"mTimeUnit":600000,"mStepCount":204,"mRunStepCount":0,"mStartTime":0},{"mSpeed":4.5708565711975098,"mCalorie":11.650000000000473,"mDistance":247.14799999999755,"mWalkStepCount":333,"mNowHealthyStep":0,"mTotalActiveTime":194653.40731424774,"mTimeUnit":600000,"mStepCount":333,"mRunStepCount":0,"mStartTime":0},{"mSpeed":4.8516430854797363,"mCalorie":8.0499999999996543,"mDistance":172.22500000000377,"mWalkStepCount":231,"mNowHealthyStep":0,"mTotalActiveTime":127793.82008475417,"mTimeUnit":600000,"mStepCount":231,"mRunStepCount":0,"mStartTime":0},{"mSpeed":5.0171852111816406,"mCalorie":9.2609999999997861,"mDistance":204.98300000000131,"mWalkStepCount":269,"mNowHealthyStep":0,"mTotalActiveTime":147082.23788824765,"mTimeUnit":600000,"mStepCount":269,"mRunStepCount":0,"mStartTime":0},{"mSpeed":6.0415711402893066,"mCalorie":8.3300000000001262,"mDistance":186.12400000000142,"mWalkStepCount":237,"mNowHealthyStep":0,"mTotalActiveTime":110905.98699763177,"mTimeUnit":600000,"mStepCount":237,"mRunStepCount":0,"mStartTime":0},{"mSpeed":5.1415553092956543,"mCalorie":18.84000000000022,"mDistance":396.06099999999481,"mWalkStepCount":527,"mNowHealthyStep":0,"mTotalActiveTime":277312.89731130435,"mTimeUnit":600000,"mStepCount":527,"mRunStepCount":0,"mStartTime":0},{"mSpeed":5.183931827545166,"mCalorie":14.518999999999433,"mDistance":320.59099999999285,"mWalkStepCount":419,"mNowHealthyStep":0,"mTotalActiveTime":222635.57211346086,"mTimeUnit":600000,"mStepCount":419,"mRunStepCount":0,"mStartTime":0},{"mSpeed":4.6212015151977539,"mCalorie":10.330000000000071,"mDistance":220.34999999999272,"mWalkStepCount":297,"mNowHealthyStep":0,"mTotalActiveTime":171656.6551033094,"mTimeUnit":600000,"mStepCount":297,"mRunStepCount":0,"mStartTime":0},{"mSpeed":4.9477686882019043,"mCalorie":6.1500000000000545,"mDistance":132.90100000000297,"mWalkStepCount":175,"mNowHealthyStep":0,"mTotalActiveTime":96698.86313251275,"mTimeUnit":600000,"mStepCount":175,"mRunStepCount":0,"mStartTime":0},{"mSpeed":4.9880838394165039,"mCalorie":9.5300000000004186,"mDistance":207.08300000000483,"mWalkStepCount":279,"mNowHealthyStep":0,"mTotalActiveTime":149455.95077860937,"mTimeUnit":600000,"mStepCount":279,"mRunStepCount":0,"mStartTime":0},{"mSpeed":5.0341553688049316,"mCalorie":10.830000000000236,"mDistance":230.27900000000403,"mWalkStepCount":306,"mNowHealthyStep":0,"mTotalActiveTime":164675.96999252227,"mTimeUnit":600000,"mStepCount":306,"mRunStepCount":0,"mStartTime":0},{"mSpeed":5.0653152465820312,"mCalorie":11.120000000000401,"mDistance":240.52200000001324,"mWalkStepCount":318,"mNowHealthyStep":0,"mTotalActiveTime":170942.80143534526,"mTimeUnit":600000,"mStepCount":318,"mRunStepCount":0,"mStartTime":0},{"mSpeed":4.8594808578491211,"mCalorie":10.710000000000163,"mDistance":232.11199999999866,"mWalkStepCount":308,"mNowHealthyStep":0,"mTotalActiveTime":171953.18925091124,"mTimeUnit":600000,"mStepCount":308,"mRunStepCount":0,"mStartTime":0},{"mSpeed":5.6366314888000488,"mCalorie":4.069999999999891,"mDistance":90.029000000001105,"mWalkStepCount":115,"mNowHealthyStep":0,"mTotalActiveTime":57499.660974213017,"mTimeUnit":600000,"mStepCount":115,"mRunStepCount":0,"mStartTime":0},{"mSpeed":5.0485959053039551,"mCalorie":10.219999999999089,"mDistance":219.38399999999646,"mWalkStepCount":289,"mNowHealthyStep":0,"mTotalActiveTime":156436.04826666293,"mTimeUnit":600000,"mStepCount":289,"mRunStepCount":0,"mStartTime":0},{"mSpeed":5.153407096862793,"mCalorie":11.729999999999745,"mDistance":258.89099999999627,"mWalkStepCount":340,"mNowHealthyStep":0,"mTotalActiveTime":180852.70773121074,"mTimeUnit":600000,"mStepCount":340,"mRunStepCount":0,"mStartTime":0},{"mSpeed":4.7613601684570312,"mCalorie":10.149999999999855,"mDistance":220.92500000000348,"mWalkStepCount":296,"mNowHealthyStep":0,"mTotalActiveTime":167038.39532962118,"mTimeUnit":600000,"mStepCount":296,"mRunStepCount":0,"mStartTime":0},{"mSpeed":4.9822168350219727,"mCalorie":7.5000000000006368,"mDistance":163.61000000000291,"mWalkStepCount":217,"mNowHealthyStep":0,"mTotalActiveTime":118219.6622137518,"mTimeUnit":600000,"mStepCount":217,"mRunStepCount":0,"mStartTime":0},{"mSpeed":4.7373743057250977,"mCalorie":9.1600000000001085,"mDistance":197.13599999999948,"mWalkStepCount":269,"mNowHealthyStep":0,"mTotalActiveTime":149806.52514188574,"mTimeUnit":600000,"mStepCount":269,"mRunStepCount":0,"mStartTime":0},{"mSpeed":5.4871082305908203,"mCalorie":14.900999999999694,"mDistance":320.47999999998893,"mWalkStepCount":408,"mNowHealthyStep":0,"mTotalActiveTime":210261.57173538726,"mTimeUnit":600000,"mStepCount":416,"mRunStepCount":8,"mStartTime":0},{"mSpeed":5.0371971130371094,"mCalorie":11.069999999999526,"mDistance":240.95399999999384,"mWalkStepCount":318,"mNowHealthyStep":0,"mTotalActiveTime":172205.77528696787,"mTimeUnit":600000,"mStepCount":318,"mRunStepCount":0,"mStartTime":0},{"mSpeed":5.1207537651062012,"mCalorie":13.708999999999849,"mDistance":304.90200000000243,"mWalkStepCount":401,"mNowHealthyStep":0,"mTotalActiveTime":214352.65781160528,"mTimeUnit":600000,"mStepCount":401,"mRunStepCount":0,"mStartTime":0},{"mSpeed":4.9867539405822754,"mCalorie":13.310000000000636,"mDistance":285.181000000003,"mWalkStepCount":375,"mNowHealthyStep":0,"mTotalActiveTime":205875.72939293686,"mTimeUnit":600000,"mStepCount":377,"mRunStepCount":2,"mStartTime":0},{"mSpeed":4.8519930839538574,"mCalorie":6.2100000000002558,"mDistance":135.28699999999486,"mWalkStepCount":180,"mNowHealthyStep":0,"mTotalActiveTime":100377.96384721171,"mTimeUnit":600000,"mStepCount":180,"mRunStepCount":0,"mStartTime":0},{"mSpeed":4.9294795989990234,"mCalorie":12.667500000000381,"mDistance":265.21900000000431,"mWalkStepCount":359,"mNowHealthyStep":0,"mTotalActiveTime":193689.49814787542,"mTimeUnit":600000,"mStepCount":359,"mRunStepCount":0,"mStartTime":0},{"mSpeed":4.9356331825256348,"mCalorie":5.4700000000000726,"mDistance":120.08600000000297,"mWalkStepCount":158,"mNowHealthyStep":0,"mTotalActiveTime":87589.490063304227,"mTimeUnit":600000,"mStepCount":159,"mRunStepCount":1,"mStartTime":0},{"mSpeed":4.96514892578125,"mCalorie":7.2399999999999993,"mDistance":149.61000000000379,"mWalkStepCount":193,"mNowHealthyStep":0,"mTotalActiveTime":108475.29171898786,"mTimeUnit":600000,"mStepCount":198,"mRunStepCount":5,"mStartTime":0},{"mSpeed":0,"mCalorie":0,"mDistance":0,"mWalkStepCount":0,"mNowHealthyStep":0,"mTotalActiveTime":0,"mTimeUnit":600000,"mStepCount":0,"mRunStepCount":0,"mStartTime":0},{"mSpeed":0,"mCalorie":0,"mDistance":0,"mWalkStepCount":0,"mNowHealthyStep":0,"mTotalActiveTime":0,"mTimeUnit":600000,"mStepCount":0,"mRunStepCount":0,"mStartTime":0},{"mSpeed":0,"mCalorie":0,"mDistance":0,"mWalkStepCount":0,"mNowHealthyStep":0,"mTotalActiveTime":0,"mTimeUnit":600000,"mStepCount":0,"mRunStepCount":0,"mStartTime":0},{"mSpeed":0,"mCalorie":0,"mDistance":0,"mWalkStepCount":0,"mNowHealthyStep":0,"mTotalActiveTime":0,"mTimeUnit":600000,"mStepCount":0,"mRunStepCount":0,"mStartTime":0},{"mSpeed":0,"mCalorie":0,"mDistance":0,"mWalkStepCount":0,"mNowHealthyStep":0,"mTotalActiveTime":0,"mTimeUnit":600000,"mStepCount":0,"mRunStepCount":0,"mStartTime":0},{"mSpeed":0,"mCalorie":0,"mDistance":0,"mWalkStepCount":0,"mNowHealthyStep":0,"mTotalActiveTime":0,"mTimeUnit":600000,"mStepCount":0,"mRunStepCount":0,"mStartTime":0},{"mSpeed":0,"mCalorie":0,"mDistance":0,"mWalkStepCount":0,"mNowHealthyStep":0,"mTotalActiveTime":0,"mTimeUnit":600000,"mStepCount":0,"mRunStepCount":0,"mStartTime":0},{"mSpeed":0,"mCalorie":0,"mDistance":0,"mWalkStepCount":0,"mNowHealthyStep":0,"mTotalActiveTime":0,"mTimeUnit":600000,"mStepCount":0,"mRunStepCount":0,"mStartTime":0},{"mSpeed":0,"mCalorie":0,"mDistance":0,"mWalkStepCount":0,"mNowHealthyStep":0,"mTotalActiveTime":0,"mTimeUnit":600000,"mStepCount":0,"mRunStepCount":0,"mStartTime":0},{"mSpeed":0,"mCalorie":0,"mDistance":0,"mWalkStepCount":0,"mNowHealthyStep":0,"mTotalActiveTime":0,"mTimeUnit":600000,"mStepCount":0,"mRunStepCount":0,"mStartTime":0},{"mSpeed":0,"mCalorie":0,"mDistance":0,"mWalkStepCount":0,"mNowHealthyStep":0,"mTotalActiveTime":0,"mTimeUnit":600000,"mStepCount":0,"mRunStepCount":0,"mStartTime":0},{"mSpeed":0,"mCalorie":0,"mDistance":0,"mWalkStepCount":0,"mNowHealthyStep":0,"mTotalActiveTime":0,"mTimeUnit":600000,"mStepCount":0,"mRunStepCount":0,"mStartTime":0},{"mSpeed":0,"mCalorie":0,"mDistance":0,"mWalkStepCount":0,"mNowHealthyStep":0,"mTotalActiveTime":0,"mTimeUnit":600000,"mStepCount":0,"mRunStepCount":0,"mStartTime":0},{"mSpeed":0,"mCalorie":0,"mDistance":0,"mWalkStepCount":0,"mNowHealthyStep":0,"mTotalActiveTime":0,"mTimeUnit":600000,"mStepCount":0,"mRunStepCount":0,"mStartTime":0},{"mSpeed":0,"mCalorie":0,"mDistance":0,"mWalkStepCount":0,"mNowHealthyStep":0,"mTotalActiveTime":0,"mTimeUnit":600000,"mStepCount":0,"mRunStepCount":0,"mStartTime":0},{"mSpeed":0,"mCalorie":0,"mDistance":0,"mWalkStepCount":0,"mNowHealthyStep":0,"mTotalActiveTime":0,"mTimeUnit":600000,"mStepCount":0,"mRunStepCount":0,"mStartTime":0},{"mSpeed":0,"mCalorie":0,"mDistance":0,"mWalkStepCount":0,"mNowHealthyStep":0,"mTotalActiveTime":0,"mTimeUnit":600000,"mStepCount":0,"mRunStepCount":0,"mStartTime":0},{"mSpeed":0,"mCalorie":0,"mDistance":0,"mWalkStepCount":0,"mNowHealthyStep":0,"mTotalActiveTime":0,"mTimeUnit":600000,"mStepCount":0,"mRunStepCount":0,"mStartTime":0},{"mSpeed":0,"mCalorie":0,"mDistance":0,"mWalkStepCount":0,"mNowHealthyStep":0,"mTotalActiveTime":0,"mTimeUnit":600000,"mStepCount":0,"mRunStepCount":0,"mStartTime":0},{"mSpeed":0,"mCalorie":0,"mDistance":0,"mWalkStepCount":0,"mNowHealthyStep":0,"mTotalActiveTime":0,"mTimeUnit":600000,"mStepCount":0,"mRunStepCount":0,"mStartTime":0},{"mSpeed":0,"mCalorie":0,"mDistance":0,"mWalkStepCount":0,"mNowHealthyStep":0,"mTotalActiveTime":0,"mTimeUnit":600000,"mStepCount":0,"mRunStepCount":0,"mStartTime":0},{"mSpeed":0,"mCalorie":0,"mDistance":0,"mWalkStepCount":0,"mNowHealthyStep":0,"mTotalActiveTime":0,"mTimeUnit":600000,"mStepCount":0,"mRunStepCount":0,"mStartTime":0},{"mSpeed":0,"mCalorie":0,"mDistance":0,"mWalkStepCount":0,"mNowHealthyStep":0,"mTotalActiveTime":0,"mTimeUnit":600000,"mStepCount":0,"mRunStepCount":0,"mStartTime":0},{"mSpeed":0,"mCalorie":0,"mDistance":0,"mWalkStepCount":0,"mNowHealthyStep":0,"mTotalActiveTime":0,"mTimeUnit":600000,"mStepCount":0,"mRunStepCount":0,"mStartTime":0},{"mSpeed":0,"mCalorie":0,"mDistance":0,"mWalkStepCount":0,"mNowHealthyStep":0,"mTotalActiveTime":0,"mTimeUnit":600000,"mStepCount":0,"mRunStepCount":0,"mStartTime":0},{"mSpeed":0,"mCalorie":0,"mDistance":0,"mWalkStepCount":0,"mNowHealthyStep":0,"mTotalActiveTime":0,"mTimeUnit":600000,"mStepCount":0,"mRunStepCount":0,"mStartTime":0},{"mSpeed":0,"mCalorie":0,"mDistance":0,"mWalkStepCount":0,"mNowHealthyStep":0,"mTotalActiveTime":0,"mTimeUnit":600000,"mStepCount":0,"mRunStepCount":0,"mStartTime":0},{"mSpeed":0,"mCalorie":0,"mDistance":0,"mWalkStepCount":0,"mNowHealthyStep":0,"mTotalActiveTime":0,"mTimeUnit":600000,"mStepCount":0,"mRunStepCount":0,"mStartTime":0},{"mSpeed":0,"mCalorie":0,"mDistance":0,"mWalkStepCount":0,"mNowHealthyStep":0,"mTotalActiveTime":0,"mTimeUnit":600000,"mStepCount":0,"mRunStepCount":0,"mStartTime":0},{"mSpeed":0,"mCalorie":0,"mDistance":0,"mWalkStepCount":0,"mNowHealthyStep":0,"mTotalActiveTime":0,"mTimeUnit":600000,"mStepCount":0,"mRunStepCount":0,"mStartTime":0},{"mSpeed":0,"mCalorie":0,"mDistance":0,"mWalkStepCount":0,"mNowHealthyStep":0,"mTotalActiveTime":0,"mTimeUnit":600000,"mStepCount":0,"mRunStepCount":0,"mStartTime":0},{"mSpeed":0,"mCalorie":0,"mDistance":0,"mWalkStepCount":0,"mNowHealthyStep":0,"mTotalActiveTime":0,"mTimeUnit":600000,"mStepCount":0,"mRunStepCount":0,"mStartTime":0},{"mSpeed":0,"mCalorie":0,"mDistance":0,"mWalkStepCount":0,"mNowHealthyStep":0,"mTotalActiveTime":0,"mTimeUnit":600000,"mStepCount":0,"mRunStepCount":0,"mStartTime":0},{"mSpeed":0,"mCalorie":0,"mDistance":0,"mWalkStepCount":0,"mNowHealthyStep":0,"mTotalActiveTime":0,"mTimeUnit":600000,"mStepCount":0,"mRunStepCount":0,"mStartTime":0},{"mSpeed":0,"mCalorie":0,"mDistance":0,"mWalkStepCount":0,"mNowHealthyStep":0,"mTotalActiveTime":0,"mTimeUnit":600000,"mStepCount":0,"mRunStepCount":0,"mStartTime":0},{"mSpeed":0,"mCalorie":0,"mDistance":0,"mWalkStepCount":0,"mNowHealthyStep":0,"mTotalActiveTime":0,"mTimeUnit":600000,"mStepCount":0,"mRunStepCount":0,"mStartTime":0},{"mSpeed":0,"mCalorie":0,"mDistance":0,"mWalkStepCount":0,"mNowHealthyStep":0,"mTotalActiveTime":0,"mTimeUnit":600000,"mStepCount":0,"mRunStepCount":0,"mStartTime":0},{"mSpeed":0,"mCalorie":0,"mDistance":0,"mWalkStepCount":0,"mNowHealthyStep":0,"mTotalActiveTime":0,"mTimeUnit":600000,"mStepCount":0,"mRunStepCount":0,"mStartTime":0},{"mSpeed":0,"mCalorie":0,"mDistance":0,"mWalkStepCount":0,"mNowHealthyStep":0,"mTotalActiveTime":0,"mTimeUnit":600000,"mStepCount":0,"mRunStepCount":0,"mStartTime":0},{"mSpeed":0,"mCalorie":0,"mDistance":0,"mWalkStepCount":0,"mNowHealthyStep":0,"mTotalActiveTime":0,"mTimeUnit":600000,"mStepCount":0,"mRunStepCount":0,"mStartTime":0},{"mSpeed":0,"mCalorie":0,"mDistance":0,"mWalkStepCount":0,"mNowHealthyStep":0,"mTotalActiveTime":0,"mTimeUnit":600000,"mStepCount":0,"mRunStepCount":0,"mStartTime":0},{"mSpeed":0,"mCalorie":0,"mDistance":0,"mWalkStepCount":0,"mNowHealthyStep":0,"mTotalActiveTime":0,"mTimeUnit":600000,"mStepCount":0,"mRunStepCount":0,"mStartTime":0},{"mSpeed":0,"mCalorie":0,"mDistance":0,"mWalkStepCount":0,"mNowHealthyStep":0,"mTotalActiveTime":0,"mTimeUnit":600000,"mStepCount":0,"mRunStepCount":0,"mStartTime":0},{"mSpeed":0,"mCalorie":0,"mDistance":0,"mWalkStepCount":0,"mNowHealthyStep":0,"mTotalActiveTime":0,"mTimeUnit":600000,"mStepCount":0,"mRunStepCount":0,"mStartTime":0},{"mSpeed":0,"mCalorie":0,"mDistance":0,"mWalkStepCount":0,"mNowHealthyStep":0,"mTotalActiveTime":0,"mTimeUnit":600000,"mStepCount":0,"mRunStepCount":0,"mStartTime":0},{"mSpeed":0,"mCalorie":0,"mDistance":0,"mWalkStepCount":0,"mNowHealthyStep":0,"mTotalActiveTime":0,"mTimeUnit":600000,"mStepCount":0,"mRunStepCount":0,"mStartTime":0},{"mSpeed":0,"mCalorie":0,"mDistance":0,"mWalkStepCount":0,"mNowHealthyStep":0,"mTotalActiveTime":0,"mTimeUnit":600000,"mStepCount":0,"mRunStepCount":0,"mStartTime":0},{"mSpeed":0,"mCalorie":0,"mDistance":0,"mWalkStepCount":0,"mNowHealthyStep":0,"mTotalActiveTime":0,"mTimeUnit":600000,"mStepCount":0,"mRunStepCount":0,"mStartTime":0},{"mSpeed":0,"mCalorie":0,"mDistance":0,"mWalkStepCount":0,"mNowHealthyStep":0,"mTotalActiveTime":0,"mTimeUnit":600000,"mStepCount":0,"mRunStepCount":0,"mStartTime":0},{"mSpeed":0,"mCalorie":0,"mDistance":0,"mWalkStepCount":0,"mNowHealthyStep":0,"mTotalActiveTime":0,"mTimeUnit":600000,"mStepCount":0,"mRunStepCount":0,"mStartTime":0},{"mSpeed":0,"mCalorie":0,"mDistance":0,"mWalkStepCount":0,"mNowHealthyStep":0,"mTotalActiveTime":0,"mTimeUnit":600000,"mStepCount":0,"mRunStepCount":0,"mStartTime":0},{"mSpeed":0,"mCalorie":0,"mDistance":0,"mWalkStepCount":0,"mNowHealthyStep":0,"mTotalActiveTime":0,"mTimeUnit":600000,"mStepCount":0,"mRunStepCount":0,"mStartTime":0},{"mSpeed":0,"mCalorie":0,"mDistance":0,"mWalkStepCount":0,"mNowHealthyStep":0,"mTotalActiveTime":0,"mTimeUnit":600000,"mStepCount":0,"mRunStepCount":0,"mStartTime":0},{"mSpeed":0,"mCalorie":0,"mDistance":0,"mWalkStepCount":0,"mNowHealthyStep":0,"mTotalActiveTime":0,"mTimeUnit":600000,"mStepCount":0,"mRunStepCount":0,"mStartTime":0},{"mSpeed":0,"mCalorie":0,"mDistance":0,"mWalkStepCount":0,"mNowHealthyStep":0,"mTotalActiveTime":0,"mTimeUnit":600000,"mStepCount":0,"mRunStepCount":0,"mStartTime":0},{"mSpeed":0,"mCalorie":0,"mDistance":0,"mWalkStepCount":0,"mNowHealthyStep":0,"mTotalActiveTime":0,"mTimeUnit":600000,"mStepCount":0,"mRunStepCount":0,"mStartTime":0},{"mSpeed":0,"mCalorie":0,"mDistance":0,"mWalkStepCount":0,"mNowHealthyStep":0,"mTotalActiveTime":0,"mTimeUnit":600000,"mStepCount":0,"mRunStepCount":0,"mStartTime":0},{"mSpeed":0,"mCalorie":0,"mDistance":0,"mWalkStepCount":0,"mNowHealthyStep":0,"mTotalActiveTime":0,"mTimeUnit":600000,"mStepCount":0,"mRunStepCount":0,"mStartTime":0},{"mSpeed":0,"mCalorie":0,"mDistance":0,"mWalkStepCount":0,"mNowHealthyStep":0,"mTotalActiveTime":0,"mTimeUnit":600000,"mStepCount":0,"mRunStepCount":0,"mStartTime":0},{"mSpeed":0,"mCalorie":0,"mDistance":0,"mWalkStepCount":0,"mNowHealthyStep":0,"mTotalActiveTime":0,"mTimeUnit":600000,"mStepCount":0,"mRunStepCount":0,"mStartTime":0}]